odoo/addons/account_template_active/README.rst
odoo/addons/account_template_active/__init__.py
odoo/addons/account_template_active/__manifest__.py
odoo/addons/account_template_active/i18n/account_template_active.pot
odoo/addons/account_template_active/i18n/es.po
odoo/addons/account_template_active/i18n/fr.po
odoo/addons/account_template_active/i18n/hr.po
odoo/addons/account_template_active/i18n/it.po
odoo/addons/account_template_active/models/__init__.py
odoo/addons/account_template_active/models/account_account_template.py
odoo/addons/account_template_active/models/account_fiscal_position_account_template.py
odoo/addons/account_template_active/models/account_fiscal_position_tax_template.py
odoo/addons/account_template_active/models/account_fiscal_position_template.py
odoo/addons/account_template_active/models/account_tax_template.py
odoo/addons/account_template_active/readme/CONTRIBUTORS.rst
odoo/addons/account_template_active/readme/DESCRIPTION.rst
odoo/addons/account_template_active/readme/USAGE.rst
odoo/addons/account_template_active/static/description/account_account_template_tree.png
odoo/addons/account_template_active/static/description/account_fiscal_position_template_form.png
odoo/addons/account_template_active/static/description/account_tax_template_tree.png
odoo/addons/account_template_active/static/description/icon.png
odoo/addons/account_template_active/static/description/index.html
odoo/addons/account_template_active/tests/__init__.py
odoo/addons/account_template_active/tests/test_module.py
odoo/addons/account_template_active/views/view_account_account_template.xml
odoo/addons/account_template_active/views/view_account_fiscal_position_template.xml
odoo/addons/account_template_active/views/view_account_tax_template.xml
odoo_addon_account_template_active-16.0.1.0.1.8.dist-info/METADATA
odoo_addon_account_template_active-16.0.1.0.1.8.dist-info/WHEEL
odoo_addon_account_template_active-16.0.1.0.1.8.dist-info/top_level.txt
odoo_addon_account_template_active-16.0.1.0.1.8.dist-info/RECORD
